lib/__init__.py
lib/hello.py
hopconnection-1.dist-info/LICENSE
hopconnection-1.dist-info/METADATA
hopconnection-1.dist-info/WHEEL
hopconnection-1.dist-info/top_level.txt
hopconnection-1.dist-info/RECORD
